apptronik_ai_mcp/__init__.py
apptronik_ai_mcp-1.0.0.dist-info/licenses/LICENSE
apptronik_ai_mcp-1.0.0.dist-info/METADATA
apptronik_ai_mcp-1.0.0.dist-info/WHEEL
apptronik_ai_mcp-1.0.0.dist-info/top_level.txt
apptronik_ai_mcp-1.0.0.dist-info/RECORD
