Metadata-Version: 2.4
Name: apptronik-ai-mcp
Version: 1.0.0
Summary: Model Context Protocol (MCP) integration for Apptronik AI - Automated Crypto Asset Management
Home-page: https://www.apptronik-ai.com
Author: Apptronik AI Team
Author-email: help@apptronik-ai.com
Classifier: Development Status :: 4 - Beta
Classifier: Intended Audience :: Developers
Classifier: License :: OSI Approved :: MIT License
Classifier: Programming Language :: Python :: 3.9
Classifier: Programming Language :: Python :: 3.10
Classifier: Programming Language :: Python :: 3.11
Requires-Python: >=3.9
License-File: LICENSE
Requires-Dist: web3>=6.11.1
Requires-Dist: solana>=0.30.2
Requires-Dist: python-binance>=1.0.19
Requires-Dist: tensorflow>=2.15.0
Requires-Dist: numpy>=1.24.0
Requires-Dist: pandas>=2.1.0
Requires-Dist: requests>=2.31.0
Requires-Dist: python-dotenv>=1.0.0
Dynamic: author
Dynamic: author-email
Dynamic: classifier
Dynamic: description
Dynamic: description-content-type
Dynamic: home-page
Dynamic: license-file
Dynamic: requires-dist
Dynamic: requires-python
Dynamic: summary
